kinaggregator/__init__.py
kinaggregator/aggregator.py
kinaggregator/deaggregator.py
kinaggregator/kpl_pb2.py
kinaggregator-0.1.1.dist-info/DESCRIPTION.rst
kinaggregator-0.1.1.dist-info/LICENSE.txt
kinaggregator-0.1.1.dist-info/METADATA
kinaggregator-0.1.1.dist-info/RECORD
kinaggregator-0.1.1.dist-info/WHEEL
kinaggregator-0.1.1.dist-info/metadata.json
kinaggregator-0.1.1.dist-info/top_level.txt
