Metadata-Version: 2.0
Name: kinaggregator
Version: 0.1.1
Summary: Python module to assist in taking advantage of the Kinesis message aggregation format for both aggregation and deaggregation.
Home-page: http://github.com/apolloFER/kinesis-aggregation-python
Author: Darko Ronic
Author-email: darko.ronic@gmail.com
License: SEE LICENSE IN LICENSE
Keywords: aws,kinesis,aggregation,deaggregation,kpl
Platform: UNKNOWN
Classifier: Development Status :: 5 - Production/Stable
Classifier: Intended Audience :: Developers
Classifier: License :: Other/Proprietary License
Classifier: Natural Language :: English
Classifier: Operating System :: OS Independent
Classifier: Programming Language :: Python
Classifier: Programming Language :: Python :: 2.7
Classifier: Programming Language :: Python :: 3.6
Classifier: Topic :: Software Development :: Libraries :: Python Modules
Classifier: Topic :: Utilities
Requires-Dist: protobuf
Requires-Dist: six
